sopel_channelmgnt/__init__.py
sopel_channelmgnt/channelmgnt/__init__.py
sopel_plugins.channelmgnt-2.1.2.dist-info/LICENSE
sopel_plugins.channelmgnt-2.1.2.dist-info/METADATA
sopel_plugins.channelmgnt-2.1.2.dist-info/WHEEL
sopel_plugins.channelmgnt-2.1.2.dist-info/entry_points.txt
sopel_plugins.channelmgnt-2.1.2.dist-info/top_level.txt
sopel_plugins.channelmgnt-2.1.2.dist-info/RECORD
